<annotation verified="yes">
                                    <folder>Annotation</folder>
                                    <filename>Cam1-From09-23-00To10-03-25_Segment_5_x264_frame_139</filename>
                                    <path>C:\Users\marina\Documents\DeepLearning\Images\Etiquetados editados\Cam1-From09-23-00To10-03-25_Segment_5_x264_output\JPEGImages\Cam1-From09-23-00To10-03-25_Segment_5_x264_frame_139.jpg</path>
                                    <source>
                                        <database>Unknown</database>
                                    </source>
                                    <size>
                                        <width>1920</width>
                                        <height>1080</height>
                                        <depth>3</depth>
                                    </size>
                                    <segmented>0</segmented>
                                    <object>
                                            <name>Handgun</name>
                                            <pose>Unspecified</pose>
                                            <truncated>0</truncated>
                                            <difficult>0</difficult>
                                            <bndbox>
                                                <xmin>1016.8595041322316</xmin>
                                                <ymin>130.86903304773566</ymin>
                                                <xmax>1043.305785123967</xmax>
                                                <ymax>167.8824969400245</ymax>
                                            </bndbox>
                                    </object>
                                    
                                    <object>
                                            <name>Short_rifle</name>
                                            <pose>Unspecified</pose>
                                            <truncated>0</truncated>
                                            <difficult>0</difficult>
                                            <bndbox>
                                                <xmin>1116.3532763532764</xmin>
                                                <ymin>97.31984503098334</ymin>
                                                <xmax>1143.2478632478633</xmax>
                                                <ymax>167.74928774928776</ymax>
                                            </bndbox>
                                    </object>
                                    
                                    <object>
                                            <name>Handgun</name>
                                            <pose>Unspecified</pose>
                                            <truncated>0</truncated>
                                            <difficult>0</difficult>
                                            <bndbox>
                                                <xmin>1146.2108818554132</xmin>
                                                <ymin>123.62393718839031</ymin>
                                                <xmax>1163.715110844017</xmax>
                                                <ymax>154.25640747418092</ymax>
                                            </bndbox>
                                    </object>
                                    </annotation>