<annotation verified="yes">
                                    <folder>Annotation</folder>
                                    <filename>Cam5-From09-27-50To09-29-30-Guns_x264_frame_292</filename>
                                    <path>C:\Users\Rodrigo\Desktop\Reetiquetado con VoTT v1\Videos Rodri\JPEGImages\Cam5-From09-27-50To09-29-30-Guns_x264_frame_292.jpg</path>
                                    <source>
                                        <database>Unknown</database>
                                    </source>
                                    <size>
                                        <width>1920</width>
                                        <height>1080</height>
                                        <depth>3</depth>
                                    </size>
                                    <segmented>0</segmented>
                                    <object>
                                            <name>Handgun</name>
                                            <pose>Unspecified</pose>
                                            <truncated>0</truncated>
                                            <difficult>0</difficult>
                                            <bndbox>
                                                <xmin>548.7603305785124</xmin>
                                                <ymin>363.52509179926557</ymin>
                                                <xmax>593.7190082644628</xmax>
                                                <ymax>412.43574051407586</ymax>
                                            </bndbox>
                                    </object>
                                    
                                    <object>
                                            <name>Handgun</name>
                                            <pose>Unspecified</pose>
                                            <truncated>0</truncated>
                                            <difficult>0</difficult>
                                            <bndbox>
                                                <xmin>134.87603305785123</xmin>
                                                <ymin>543.3047735618114</ymin>
                                                <xmax>186.44628099173553</xmax>
                                                <ymax>589.5716034271726</ymax>
                                            </bndbox>
                                    </object>
                                    </annotation>