<annotation verified="yes">
                                    <folder>Annotation</folder>
                                    <filename>Cam5-From09-24-18To09-26-43-Guns_x264_Segment_0_x264_frame_46</filename>
                                    <path>C:\Users\marina\Documents\DeepLearning\Images\Etiquetados editados\Cam5-From09-24-18To09-26-43-Guns_x264_Segment_0_x264_output\JPEGImages\Cam5-From09-24-18To09-26-43-Guns_x264_Segment_0_x264_frame_46.jpg</path>
                                    <source>
                                        <database>Unknown</database>
                                    </source>
                                    <size>
                                        <width>1920</width>
                                        <height>1080</height>
                                        <depth>3</depth>
                                    </size>
                                    <segmented>0</segmented>
                                    <object>
                                            <name>Handgun</name>
                                            <pose>Unspecified</pose>
                                            <truncated>0</truncated>
                                            <difficult>0</difficult>
                                            <bndbox>
                                                <xmin>830.4132231404959</xmin>
                                                <ymin>453.4149326805385</ymin>
                                                <xmax>893.8842975206612</xmax>
                                                <ymax>524.7980416156671</ymax>
                                            </bndbox>
                                    </object>
                                    
                                    <object>
                                            <name>Handgun</name>
                                            <pose>Unspecified</pose>
                                            <truncated>0</truncated>
                                            <difficult>0</difficult>
                                            <bndbox>
                                                <xmin>399.3388429752066</xmin>
                                                <ymin>462.66829865361075</ymin>
                                                <xmax>435.0413223140496</xmax>
                                                <ymax>516.8665850673194</ymax>
                                            </bndbox>
                                    </object>
                                    
                                    <object>
                                            <name>Handgun</name>
                                            <pose>Unspecified</pose>
                                            <truncated>0</truncated>
                                            <difficult>0</difficult>
                                            <bndbox>
                                                <xmin>551.404958677686</xmin>
                                                <ymin>413.75764993880045</ymin>
                                                <xmax>577.8512396694215</xmax>
                                                <ymax>469.2778457772338</ymax>
                                            </bndbox>
                                    </object>
                                    </annotation>